TextSpotter
