Metadata-Version: 1.0
Name: CsuTextSpotter
Version: 1.0.28
Summary: person or car
Home-page: UNKNOWN
Author: csu_ywj
Author-email: UNKNOWN
License: MIT Licence
Keywords: pip
Platform: any
